graphid/__init__.py
graphid/__init__.pyi
graphid/__main__.py
graphid/api.py
graphid/core/__init__.py
graphid/core/__init__.pyi
graphid/core/__main__.py
graphid/core/_rhomb_dist.py
graphid/core/annot_inference.py
graphid/core/mixin_callbacks.py
graphid/core/mixin_dynamic.py
graphid/core/mixin_helpers.py
graphid/core/mixin_invariants.py
graphid/core/mixin_loops.py
graphid/core/mixin_priority.py
graphid/core/mixin_redundancy.py
graphid/core/mixin_simulation.py
graphid/core/mixin_viz.py
graphid/core/refresh.py
graphid/core/state.py
graphid/demo/__init__.py
graphid/demo/__init__.pyi
graphid/demo/__main__.py
graphid/demo/demo_script.py
graphid/demo/dummy_algos.py
graphid/demo/dummy_infr.py
graphid/ibeis/__init__.py
graphid/ibeis/ibeis_demo.py
graphid/ibeis/ibeis_matching.py
graphid/ibeis/mixin_groundtruth.py
graphid/ibeis/mixin_ibeis.py
graphid/ibeis/mixin_matching.py
graphid/rc/__init__.py
graphid/rc/registry.py
graphid/rc/requirements/__init__.py
graphid/rc/requirements/docs.txt
graphid/rc/requirements/graphics.txt
graphid/rc/requirements/headless.txt
graphid/rc/requirements/optional.txt
graphid/rc/requirements/problematic.txt
graphid/rc/requirements/runtime.txt
graphid/rc/requirements/tests.txt
graphid/util/__init__.py
graphid/util/__init__.pyi
graphid/util/mpl_plottool.py
graphid/util/mplutil.py
graphid/util/name_rectifier.py
graphid/util/nx_dynamic_graph.py
graphid/util/nx_utils.py
graphid/util/priority_queue.py
graphid/util/util_boxes.py
graphid/util/util_grabdata.py
graphid/util/util_graphviz.py
graphid/util/util_group.py
graphid/util/util_image.py
graphid/util/util_kw.py
graphid/util/util_misc.py
graphid/util/util_numpy.py
graphid/util/util_random.py
graphid/util/util_tags.py
requirements/__init__.py
requirements/docs.txt
requirements/graphics.txt
requirements/headless.txt
requirements/optional.txt
requirements/problematic.txt
requirements/runtime.txt
requirements/tests.txt
tests/__init__.py
tests/dyn_cases.py
tests/mst_debug.py
tests/test_graph_iden.py
graphid-0.1.2.dist-info/LICENSE
graphid-0.1.2.dist-info/METADATA
graphid-0.1.2.dist-info/WHEEL
graphid-0.1.2.dist-info/top_level.txt
graphid-0.1.2.dist-info/RECORD
